LICENSE
README.md
setup.py
vgio/__init__.py
vgio.egg-info/PKG-INFO
vgio.egg-info/SOURCES.txt
vgio.egg-info/dependency_links.txt
vgio.egg-info/top_level.txt
vgio/_core/__init__.py
vgio/devildaggers/__init__.py
vgio/devildaggers/hxmesh.py
vgio/devildaggers/hxresourcegroup.py
vgio/devildaggers/hxshader.py
vgio/devildaggers/hxtexture.py
vgio/duke3d/__init__.py
vgio/duke3d/art.py
vgio/duke3d/grp.py
vgio/duke3d/map.py
vgio/hexen2/__init__.py
vgio/hexen2/bsp.py
vgio/hrot/__init__.py
vgio/hrot/pak.py
vgio/quake/__init__.py
vgio/quake/dem.py
vgio/quake/lmp.py
vgio/quake/map.py
vgio/quake/mdl.py
vgio/quake/pak.py
vgio/quake/protocol.py
vgio/quake/spr.py
vgio/quake/wad.py
vgio/quake2/__init__.py
vgio/quake2/bsp.py
vgio/quake2/dm2.py
vgio/quake2/md2.py
vgio/quake2/pak.py
vgio/quake2/pcx.py
vgio/quake2/protocol.py
vgio/quake2/sp2.py
vgio/quake2/wal.py
vgio/quake/bsp/__init__.py
vgio/quake/bsp/bsp29.py
vgio/quake/bsp/bsp29a.py