Metadata-Version: 2.1
Name: vgio
Version: 1.3.0
Summary: Video Game IO
Home-page: https://github.com/JoshuaSkelly/vgio
Author: Joshua Skelton
Author-email: joshua.skelton@gmail.com
License: MIT
Platform: UNKNOWN
